julep_cli/__init__.py
julep_cli/__main__.py
julep_cli/agents.py
julep_cli/app.py
julep_cli/auth.py
julep_cli/chat.py
julep_cli/executions.py
julep_cli/importt.py
julep_cli/init.py
julep_cli/logs.py
julep_cli/ls.py
julep_cli/models.py
julep_cli/run.py
julep_cli/sync.py
julep_cli/tasks.py
julep_cli/tools.py
julep_cli/utils.py
julep_cli/wrapper.py
julep_cli-0.1.11.dist-info/METADATA
julep_cli-0.1.11.dist-info/WHEEL
julep_cli-0.1.11.dist-info/entry_points.txt
julep_cli-0.1.11.dist-info/top_level.txt
julep_cli-0.1.11.dist-info/RECORD
