Metadata-Version: 2.2
Name: julep-cli
Version: 0.1.11
Summary: Julep CLI
Author-email: Julep <developers@julep.ai>
Requires-Python: <3.13,>=3.11
Requires-Dist: anyio~=4.4.0
Requires-Dist: beartype~=0.18.5
Requires-Dist: environs~=10.3.0
Requires-Dist: jsonschema~=4.22.0
Requires-Dist: openai~=1.55.0
Requires-Dist: pandas~=2.2.2
Requires-Dist: pydantic[email]~=2.10.2
Requires-Dist: uvloop~=0.21.0
Requires-Dist: xxhash~=3.5.0
Requires-Dist: unique-namer>=1.6.1
Requires-Dist: typer>=0.15.1
Requires-Dist: textual>=1.0.0
Requires-Dist: trogon[typer]>=0.6.0
Requires-Dist: typer-config[yaml]>=1.4.2
Requires-Dist: julep>=1.56.0
Requires-Dist: questionary>=2.1.0
Requires-Dist: db-sqlite3>=0.0.1
Requires-Dist: stringcase>=1.2.0
Requires-Dist: pyjwt>=2.10.1
Requires-Dist: watchdog>=6.0.0
